.deepsource.toml
.gitignore
.pre-commit-config.yaml
.stickler.yml
CHANGELOG.md
LICENSE
README.md
conftest.py
environment.yml
pyproject.toml
setup.cfg
.github/dependabot.yml
.github/workflows/codeql.yml
.github/workflows/etchosts.txt
.github/workflows/main.yml
data/product_examples/1hrad.20130920.190000.gz
data/product_examples/AFD.txt
data/product_examples/AFDDMX.txt
data/product_examples/AFDMST.txt
data/product_examples/AFDPQ.txt
data/product_examples/AFD_noMND.txt
data/product_examples/CAEIA.txt
data/product_examples/CCA.txt
data/product_examples/CCFMOB.txt
data/product_examples/CHST.txt
data/product_examples/DSW.txt
data/product_examples/FFA.txt
data/product_examples/FFGAMA.txt
data/product_examples/FFGJAN.txt
data/product_examples/FFGKY.txt
data/product_examples/FFWTWC_tilde.txt
data/product_examples/FLSBOU.txt
data/product_examples/FLSBRO_nomnd.txt
data/product_examples/FLSDMX.txt
data/product_examples/FLSGRB.txt
data/product_examples/FLSICT.txt
data/product_examples/FLSLZK_notime.txt
data/product_examples/FLSMKX.txt
data/product_examples/FLSRAH.txt
data/product_examples/FLSTWC.txt
data/product_examples/FLWBOI.txt
data/product_examples/FLWGRB.txt
data/product_examples/FLWHGX_ccw.txt
data/product_examples/FLWLCH.txt
data/product_examples/FLWLZK.txt
data/product_examples/FLWMKX_ROU.txt
data/product_examples/FLW_badgeom.txt
data/product_examples/FLW_badugc.txt
data/product_examples/HLS.txt
data/product_examples/MANANN.txt
data/product_examples/MAVWC0.txt
data/product_examples/MWSKEY.txt
data/product_examples/MWSMFL.txt
data/product_examples/MWWBRO.txt
data/product_examples/MWWLWX.txt
data/product_examples/MWWLWX_dups.txt
data/product_examples/MWWLWX_twovtec.txt
data/product_examples/MWWSEW.txt
data/product_examples/MWWspanish.txt
data/product_examples/NOWDMX.txt
data/product_examples/PMDSA.txt
data/product_examples/RECFGZ.txt
data/product_examples/RFDOAX.txt
data/product_examples/RFWBOI_fakeugc.txt
data/product_examples/RFWSEW.txt
data/product_examples/RTPSGX.txt
src/pyiem.egg-info/PKG-INFO
src/pyiem.egg-info/SOURCES.txt
src/pyiem.egg-info/dependency_links.txt
src/pyiem.egg-info/requires.txt
src/pyiem.egg-info/top_level.txt
