Metadata-Version: 2.4
Name: pyiem
Version: 1.25.0
Summary: Collection of things that may help with processing weather data.
License-Expression: MIT
Project-URL: homepage, https://github.com/akrherz/pyIEM
Keywords: meteorology
License-File: LICENSE
Requires-Dist: affine
Requires-Dist: defusedxml
Requires-Dist: docutils
Requires-Dist: geopandas
Requires-Dist: httpx
Requires-Dist: jinja2
Requires-Dist: matplotlib>=3.5.0
Requires-Dist: metar
Requires-Dist: metpy
Requires-Dist: netCDF4
Requires-Dist: numpy
Requires-Dist: pandas
Requires-Dist: paste
Requires-Dist: pillow
Requires-Dist: pyarrow
Requires-Dist: pydantic
Requires-Dist: pygrib
Requires-Dist: pymemcache
Requires-Dist: pyogrio
Requires-Dist: pyproj
Requires-Dist: psycopg
Requires-Dist: rasterio
Requires-Dist: rasterstats
Requires-Dist: scipy
Requires-Dist: shapely
Requires-Dist: sqlalchemy>=2
Requires-Dist: xarray
Dynamic: license-file
